aiq/meta/pypi.md
aiq/plugins/opentelemetry/__init__.py
aiq/plugins/opentelemetry/otel_span.py
aiq/plugins/opentelemetry/otel_span_exporter.py
aiq/plugins/opentelemetry/otlp_span_adapter_exporter.py
aiq/plugins/opentelemetry/register.py
aiq/plugins/opentelemetry/span_converter.py
aiq/plugins/opentelemetry/mixin/__init__.py
aiq/plugins/opentelemetry/mixin/otlp_span_exporter_mixin.py
aiqtoolkit_opentelemetry-1.2.0a20250806.dist-info/METADATA
aiqtoolkit_opentelemetry-1.2.0a20250806.dist-info/WHEEL
aiqtoolkit_opentelemetry-1.2.0a20250806.dist-info/entry_points.txt
aiqtoolkit_opentelemetry-1.2.0a20250806.dist-info/top_level.txt
aiqtoolkit_opentelemetry-1.2.0a20250806.dist-info/RECORD
