Metadata-Version: 2.4
Name: aiqtoolkit-opentelemetry
Version: 1.2.0a20250806
Summary: Subpackage for Weave integration in AIQtoolkit
Keywords: ai,observability,opentelemetry
Classifier: Programming Language :: Python
Requires-Python: <3.13,>=3.11
Requires-Dist: aiqtoolkit==v1.2.0a20250806
Requires-Dist: opentelemetry-api~=1.2
Requires-Dist: opentelemetry-exporter-otlp~=1.3
Requires-Dist: opentelemetry-sdk~=1.3
